[
    {
        "P_ELEMENT_ITEM_ID": "1000",
        "P_NAME": "\u7dd1\u58ee\u8349",
        "8Cx57oAk": "\u7dd1\u58ee\u8349",
        "P_RARE": "1",
        "P_DISPORDER": "1000",
        "CA7uXs6D": "99",
        "P_DISP_DICTIONARY": "0",
        "P_ICON_ID": "100",
        "60IsqxDt": "1",
        "o7e4HXMP": "1,1,0,1,0,0,0,0",
        "P_DOUBLE_SPHERE_TRIGGER": "0,0,0,0",
        "P_DICTIONARY_NO": "1",
        "P_DICTIONARY_BG": "2",
        "T04pJPmh": "",
        "P_NEED_SWITCH_INFO": "0",
        "P_HIDE_SWITCH_INFO": "0",
        "P_OPEN_SWITCH_INFO": "0"
    },
    {
        "P_ELEMENT_ITEM_ID": "1001",
        "P_NAME": "\u9752\u80c6\u8349",
        "8Cx57oAk": "\u9752\u80c6\u8349",
        "P_RARE": "2",
        "P_DISPORDER": "1001",
        "CA7uXs6D": "99",
        "P_DISP_DICTIONARY": "0",
        "P_ICON_ID": "101",
        "60IsqxDt": "1",
        "o7e4HXMP": "1,1,0,1,0,0,0,0",
        "P_DOUBLE_SPHERE_TRIGGER": "0,0,0,0",
        "P_DICTIONARY_NO": "1",
        "P_DICTIONARY_BG": "3",
        "T04pJPmh": "",
        "P_NEED_SWITCH_INFO": "0",
        "P_HIDE_SWITCH_INFO": "0",
        "P_OPEN_SWITCH_INFO": "0"
    },
    {
        "P_ELEMENT_ITEM_ID": "2000",
        "P_NAME": "\u30c9\u30f3\u306e\u5b9f",
        "8Cx57oAk": "\u30c9\u30f3\u306e\u5b9f",
        "P_RARE": "1",
        "P_DISPORDER": "2000",
        "CA7uXs6D": "99",
        "P_DISP_DICTIONARY": "0",
        "P_ICON_ID": "205",
        "60IsqxDt": "1",
        "o7e4HXMP": "1,1,0,1,0,0,0,0",
        "P_DOUBLE_SPHERE_TRIGGER": "0,0,0,0",
        "P_DICTIONARY_NO": "1",
        "P_DICTIONARY_BG": "5",
        "T04pJPmh": "",
        "P_NEED_SWITCH_INFO": "0",
        "P_HIDE_SWITCH_INFO": "0",
        "P_OPEN_SWITCH_INFO": "0"
    },
    {
        "P_ELEMENT_ITEM_ID": "2001",
        "P_NAME": "\u30d3\u30a6\u306e\u5b9f",
        "8Cx57oAk": "\u30d3\u30a6\u306e\u5b9f",
        "P_RARE": "1",
        "P_DISPORDER": "2001",
        "CA7uXs6D": "99",
        "P_DISP_DICTIONARY": "0",
        "P_ICON_ID": "200",
        "60IsqxDt": "1",
        "o7e4HXMP": "1,1,0,1,0,0,0,0",
        "P_DOUBLE_SPHERE_TRIGGER": "0,0,0,0",
        "P_DICTIONARY_NO": "1",
        "P_DICTIONARY_BG": "6",
        "T04pJPmh": "",
        "P_NEED_SWITCH_INFO": "0",
        "P_HIDE_SWITCH_INFO": "0",
        "P_OPEN_SWITCH_INFO": "0"
    },
    {
        "P_ELEMENT_ITEM_ID": "2002",
        "P_NAME": "\u30b9\u30ba\u306e\u5b9f",
        "8Cx57oAk": "\u30b9\u30ba\u306e\u5b9f",
        "P_RARE": "1",
        "P_DISPORDER": "2002",
        "CA7uXs6D": "99",
        "P_DISP_DICTIONARY": "0",
        "P_ICON_ID": "206",
        "60IsqxDt": "1",
        "o7e4HXMP": "1,1,0,1,0,0,0,0",
        "P_DOUBLE_SPHERE_TRIGGER": "0,0,0,0",
        "P_DICTIONARY_NO": "1",
        "P_DICTIONARY_BG": "7",
        "T04pJPmh": "",
        "P_NEED_SWITCH_INFO": "0",
        "P_HIDE_SWITCH_INFO": "0",
        "P_OPEN_SWITCH_INFO": "0"
    },
    {
        "P_ELEMENT_ITEM_ID": "2100",
        "P_NAME": "\u30b3\u30af\u306e\u5b9f",
        "8Cx57oAk": "\u30b3\u30af\u306e\u5b9f",
        "P_RARE": "2",
        "P_DISPORDER": "2100",
        "CA7uXs6D": "99",
        "P_DISP_DICTIONARY": "0",
        "P_ICON_ID": "204",
        "60IsqxDt": "1",
        "o7e4HXMP": "1,1,0,1,0,0,0,0",
        "P_DOUBLE_SPHERE_TRIGGER": "0,0,0,0",
        "P_DICTIONARY_NO": "1",
        "P_DICTIONARY_BG": "9",
        "T04pJPmh": "",
        "P_NEED_SWITCH_INFO": "0",
        "P_HIDE_SWITCH_INFO": "0",
        "P_OPEN_SWITCH_INFO": "0"
    },
    {
        "P_ELEMENT_ITEM_ID": "2101",
        "P_NAME": "\u30db\u30af\u306e\u5b9f",
        "8Cx57oAk": "\u30db\u30af\u306e\u5b9f",
        "P_RARE": "2",
        "P_DISPORDER": "2101",
        "CA7uXs6D": "99",
        "P_DISP_DICTIONARY": "0",
        "P_ICON_ID": "201",
        "60IsqxDt": "1",
        "o7e4HXMP": "1,1,0,1,0,0,0,0",
        "P_DOUBLE_SPHERE_TRIGGER": "0,0,0,0",
        "P_DICTIONARY_NO": "1",
        "P_DICTIONARY_BG": "10",
        "T04pJPmh": "",
        "P_NEED_SWITCH_INFO": "0",
        "P_HIDE_SWITCH_INFO": "0",
        "P_OPEN_SWITCH_INFO": "0"
    },
    {
        "P_ELEMENT_ITEM_ID": "3000",
        "P_NAME": "\u6e05\u7fe0\u306e\u96eb",
        "8Cx57oAk": "\u6e05\u7fe0\u306e\u96eb",
        "P_RARE": "1",
        "P_DISPORDER": "3000",
        "CA7uXs6D": "99",
        "P_DISP_DICTIONARY": "0",
        "P_ICON_ID": "250",
        "60IsqxDt": "1",
        "o7e4HXMP": "1,1,0,1,0,0,0,0",
        "P_DOUBLE_SPHERE_TRIGGER": "0,0,0,0",
        "P_DICTIONARY_NO": "1",
        "P_DICTIONARY_BG": "11",
        "T04pJPmh": "",
        "P_NEED_SWITCH_INFO": "0",
        "P_HIDE_SWITCH_INFO": "0",
        "P_OPEN_SWITCH_INFO": "0"
    },
    {
        "P_ELEMENT_ITEM_ID": "3001",
        "P_NAME": "\u7d14\u85cd\u306e\u96eb",
        "8Cx57oAk": "\u7d14\u85cd\u306e\u96eb",
        "P_RARE": "2",
        "P_DISPORDER": "3001",
        "CA7uXs6D": "99",
        "P_DISP_DICTIONARY": "0",
        "P_ICON_ID": "251",
        "60IsqxDt": "1",
        "o7e4HXMP": "1,1,0,1,0,0,0,0",
        "P_DOUBLE_SPHERE_TRIGGER": "0,0,0,0",
        "P_DICTIONARY_NO": "1",
        "P_DICTIONARY_BG": "12",
        "T04pJPmh": "",
        "P_NEED_SWITCH_INFO": "0",
        "P_HIDE_SWITCH_INFO": "0",
        "P_OPEN_SWITCH_INFO": "0"
    },
    {
        "P_ELEMENT_ITEM_ID": "3002",
        "P_NAME": "\u6ec5\u6731\u306e\u96eb",
        "8Cx57oAk": "\u6ec5\u6731\u306e\u96eb",
        "P_RARE": "3",
        "P_DISPORDER": "3002",
        "CA7uXs6D": "99",
        "P_DISP_DICTIONARY": "0",
        "P_ICON_ID": "254",
        "60IsqxDt": "1",
        "o7e4HXMP": "1,1,0,1,0,0,0,0",
        "P_DOUBLE_SPHERE_TRIGGER": "0,0,0,0",
        "P_DICTIONARY_NO": "1",
        "P_DICTIONARY_BG": "13",
        "T04pJPmh": "",
        "P_NEED_SWITCH_INFO": "0",
        "P_HIDE_SWITCH_INFO": "0",
        "P_OPEN_SWITCH_INFO": "0"
    },
    {
        "P_ELEMENT_ITEM_ID": "4000",
        "P_NAME": "\u6b66\u795e\u306e\u773c",
        "8Cx57oAk": "\u6b66\u795e\u306e\u773c",
        "P_RARE": "3",
        "P_DISPORDER": "4000",
        "CA7uXs6D": "99",
        "P_DISP_DICTIONARY": "0",
        "P_ICON_ID": "403",
        "60IsqxDt": "1",
        "o7e4HXMP": "1,1,0,1,0,0,0,0",
        "P_DOUBLE_SPHERE_TRIGGER": "0,0,0,0",
        "P_DICTIONARY_NO": "1",
        "P_DICTIONARY_BG": "16",
        "T04pJPmh": "",
        "P_NEED_SWITCH_INFO": "0",
        "P_HIDE_SWITCH_INFO": "0",
        "P_OPEN_SWITCH_INFO": "0"
    },
    {
        "P_ELEMENT_ITEM_ID": "4001",
        "P_NAME": "\u708e\u795e\u306e\u773c",
        "8Cx57oAk": "\u708e\u795e\u306e\u773c",
        "P_RARE": "3",
        "P_DISPORDER": "4001",
        "CA7uXs6D": "99",
        "P_DISP_DICTIONARY": "0",
        "P_ICON_ID": "404",
        "60IsqxDt": "1",
        "o7e4HXMP": "1,1,0,1,0,0,0,0",
        "P_DOUBLE_SPHERE_TRIGGER": "0,0,0,0",
        "P_DICTIONARY_NO": "1",
        "P_DICTIONARY_BG": "17",
        "T04pJPmh": "",
        "P_NEED_SWITCH_INFO": "0",
        "P_HIDE_SWITCH_INFO": "0",
        "P_OPEN_SWITCH_INFO": "0"
    },
    {
        "P_ELEMENT_ITEM_ID": "4002",
        "P_NAME": "\u6c34\u795e\u306e\u773c",
        "8Cx57oAk": "\u6c34\u795e\u306e\u773c",
        "P_RARE": "3",
        "P_DISPORDER": "4002",
        "CA7uXs6D": "99",
        "P_DISP_DICTIONARY": "0",
        "P_ICON_ID": "401",
        "60IsqxDt": "1",
        "o7e4HXMP": "1,1,0,1,0,0,0,0",
        "P_DOUBLE_SPHERE_TRIGGER": "0,0,0,0",
        "P_DICTIONARY_NO": "1",
        "P_DICTIONARY_BG": "18",
        "T04pJPmh": "",
        "P_NEED_SWITCH_INFO": "0",
        "P_HIDE_SWITCH_INFO": "0",
        "P_OPEN_SWITCH_INFO": "0"
    },
    {
        "P_ELEMENT_ITEM_ID": "4003",
        "P_NAME": "\u6a39\u795e\u306e\u773c",
        "8Cx57oAk": "\u6a39\u795e\u306e\u773c",
        "P_RARE": "3",
        "P_DISPORDER": "4003",
        "CA7uXs6D": "99",
        "P_DISP_DICTIONARY": "0",
        "P_ICON_ID": "400",
        "60IsqxDt": "1",
        "o7e4HXMP": "1,1,0,1,0,0,0,0",
        "P_DOUBLE_SPHERE_TRIGGER": "0,0,0,0",
        "P_DICTIONARY_NO": "1",
        "P_DICTIONARY_BG": "19",
        "T04pJPmh": "",
        "P_NEED_SWITCH_INFO": "0",
        "P_HIDE_SWITCH_INFO": "0",
        "P_OPEN_SWITCH_INFO": "0"
    },
    {
        "P_ELEMENT_ITEM_ID": "4004",
        "P_NAME": "\u96f7\u795e\u306e\u773c",
        "8Cx57oAk": "\u96f7\u795e\u306e\u773c",
        "P_RARE": "3",
        "P_DISPORDER": "4004",
        "CA7uXs6D": "99",
        "P_DISP_DICTIONARY": "0",
        "P_ICON_ID": "402",
        "60IsqxDt": "1",
        "o7e4HXMP": "1,1,0,1,0,0,0,0",
        "P_DOUBLE_SPHERE_TRIGGER": "0,0,0,0",
        "P_DICTIONARY_NO": "1",
        "P_DICTIONARY_BG": "20",
        "T04pJPmh": "",
        "P_NEED_SWITCH_INFO": "0",
        "P_HIDE_SWITCH_INFO": "0",
        "P_OPEN_SWITCH_INFO": "0"
    },
    {
        "P_ELEMENT_ITEM_ID": "4005",
        "P_NAME": "\u5149\u795e\u306e\u773c",
        "8Cx57oAk": "\u5149\u795e\u306e\u773c",
        "P_RARE": "3",
        "P_DISPORDER": "4005",
        "CA7uXs6D": "99",
        "P_DISP_DICTIONARY": "0",
        "P_ICON_ID": "406",
        "60IsqxDt": "1",
        "o7e4HXMP": "1,1,0,1,0,0,0,0",
        "P_DOUBLE_SPHERE_TRIGGER": "0,0,0,0",
        "P_DICTIONARY_NO": "1",
        "P_DICTIONARY_BG": "21",
        "T04pJPmh": "",
        "P_NEED_SWITCH_INFO": "0",
        "P_HIDE_SWITCH_INFO": "0",
        "P_OPEN_SWITCH_INFO": "0"
    },
    {
        "P_ELEMENT_ITEM_ID": "4006",
        "P_NAME": "\u95c7\u795e\u306e\u773c",
        "8Cx57oAk": "\u95c7\u795e\u306e\u773c",
        "P_RARE": "3",
        "P_DISPORDER": "4006",
        "CA7uXs6D": "99",
        "P_DISP_DICTIONARY": "0",
        "P_ICON_ID": "405",
        "60IsqxDt": "1",
        "o7e4HXMP": "1,1,0,1,0,0,0,0",
        "P_DOUBLE_SPHERE_TRIGGER": "0,0,0,0",
        "P_DICTIONARY_NO": "1",
        "P_DICTIONARY_BG": "22",
        "T04pJPmh": "",
        "P_NEED_SWITCH_INFO": "0",
        "P_HIDE_SWITCH_INFO": "0",
        "P_OPEN_SWITCH_INFO": "0"
    },
    {
        "P_ELEMENT_ITEM_ID": "5000",
        "P_NAME": "\u786c\u5ca9\u7363\u9aa8",
        "8Cx57oAk": "\u786c\u5ca9\u7363\u9aa8",
        "P_RARE": "3",
        "P_DISPORDER": "5000",
        "CA7uXs6D": "99",
        "P_DISP_DICTIONARY": "0",
        "P_ICON_ID": "506",
        "60IsqxDt": "1",
        "o7e4HXMP": "1,1,0,1,0,0,0,0",
        "P_DOUBLE_SPHERE_TRIGGER": "0,0,0,0",
        "P_DICTIONARY_NO": "1",
        "P_DICTIONARY_BG": "23",
        "T04pJPmh": "",
        "P_NEED_SWITCH_INFO": "0",
        "P_HIDE_SWITCH_INFO": "0",
        "P_OPEN_SWITCH_INFO": "0"
    },
    {
        "P_ELEMENT_ITEM_ID": "5001",
        "P_NAME": "\u7dd1\u7363\u306e\u9aa8",
        "8Cx57oAk": "\u7dd1\u7363\u306e\u9aa8",
        "P_RARE": "1",
        "P_DISPORDER": "5001",
        "CA7uXs6D": "99",
        "P_DISP_DICTIONARY": "0",
        "P_ICON_ID": "500",
        "60IsqxDt": "1",
        "o7e4HXMP": "1,1,0,1,0,0,0,0",
        "P_DOUBLE_SPHERE_TRIGGER": "0,0,0,0",
        "P_DICTIONARY_NO": "1",
        "P_DICTIONARY_BG": "24",
        "T04pJPmh": "",
        "P_NEED_SWITCH_INFO": "0",
        "P_HIDE_SWITCH_INFO": "0",
        "P_OPEN_SWITCH_INFO": "0"
    },
    {
        "P_ELEMENT_ITEM_ID": "5002",
        "P_NAME": "\u9752\u7363\u306e\u9aa8",
        "8Cx57oAk": "\u9752\u7363\u306e\u9aa8",
        "P_RARE": "2",
        "P_DISPORDER": "5002",
        "CA7uXs6D": "99",
        "P_DISP_DICTIONARY": "0",
        "P_ICON_ID": "501",
        "60IsqxDt": "1",
        "o7e4HXMP": "1,1,0,1,0,0,0,0",
        "P_DOUBLE_SPHERE_TRIGGER": "0,0,0,0",
        "P_DICTIONARY_NO": "1",
        "P_DICTIONARY_BG": "25",
        "T04pJPmh": "",
        "P_NEED_SWITCH_INFO": "0",
        "P_HIDE_SWITCH_INFO": "0",
        "P_OPEN_SWITCH_INFO": "0"
    },
    {
        "P_ELEMENT_ITEM_ID": "5003",
        "P_NAME": "\u8d64\u7363\u306e\u9aa8",
        "8Cx57oAk": "\u8d64\u7363\u306e\u9aa8",
        "P_RARE": "3",
        "P_DISPORDER": "5003",
        "CA7uXs6D": "99",
        "P_DISP_DICTIONARY": "0",
        "P_ICON_ID": "504",
        "60IsqxDt": "1",
        "o7e4HXMP": "1,1,0,1,0,0,0,0",
        "P_DOUBLE_SPHERE_TRIGGER": "0,0,0,0",
        "P_DICTIONARY_NO": "1",
        "P_DICTIONARY_BG": "26",
        "T04pJPmh": "",
        "P_NEED_SWITCH_INFO": "0",
        "P_HIDE_SWITCH_INFO": "0",
        "P_OPEN_SWITCH_INFO": "0"
    },
    {
        "P_ELEMENT_ITEM_ID": "6000",
        "P_NAME": "\u795e\u53b3\u5fa1\u77f3",
        "8Cx57oAk": "\u795e\u53b3\u5fa1\u77f3",
        "P_RARE": "3",
        "P_DISPORDER": "6000",
        "CA7uXs6D": "99",
        "P_DISP_DICTIONARY": "0",
        "P_ICON_ID": "552",
        "60IsqxDt": "1",
        "o7e4HXMP": "1,1,0,1,0,0,0,0",
        "P_DOUBLE_SPHERE_TRIGGER": "0,0,0,0",
        "P_DICTIONARY_NO": "1",
        "P_DICTIONARY_BG": "27",
        "T04pJPmh": "",
        "P_NEED_SWITCH_INFO": "0",
        "P_HIDE_SWITCH_INFO": "0",
        "P_OPEN_SWITCH_INFO": "0"
    },
    {
        "P_ELEMENT_ITEM_ID": "6002",
        "P_NAME": "\u5275\u9b42\u5fa1\u77f3",
        "8Cx57oAk": "\u5275\u9b42\u5fa1\u77f3",
        "P_RARE": "4",
        "P_DISPORDER": "6002",
        "CA7uXs6D": "99",
        "P_DISP_DICTIONARY": "0",
        "P_ICON_ID": "553",
        "60IsqxDt": "1",
        "o7e4HXMP": "1,1,0,1,0,0,0,0",
        "P_DOUBLE_SPHERE_TRIGGER": "0,0,0,0",
        "P_DICTIONARY_NO": "1",
        "P_DICTIONARY_BG": "29",
        "T04pJPmh": "",
        "P_NEED_SWITCH_INFO": "0",
        "P_HIDE_SWITCH_INFO": "0",
        "P_OPEN_SWITCH_INFO": "0"
    },
    {
        "P_ELEMENT_ITEM_ID": "7000",
        "P_NAME": "\u7dd1\u7363\u306e\u722a",
        "8Cx57oAk": "\u7dd1\u7363\u306e\u722a",
        "P_RARE": "1",
        "P_DISPORDER": "7000",
        "CA7uXs6D": "99",
        "P_DISP_DICTIONARY": "0",
        "P_ICON_ID": "300",
        "60IsqxDt": "1",
        "o7e4HXMP": "1,1,0,1,0,0,0,0",
        "P_DOUBLE_SPHERE_TRIGGER": "0,0,0,0",
        "P_DICTIONARY_NO": "1",
        "P_DICTIONARY_BG": "30",
        "T04pJPmh": "",
        "P_NEED_SWITCH_INFO": "0",
        "P_HIDE_SWITCH_INFO": "0",
        "P_OPEN_SWITCH_INFO": "0"
    },
    {
        "P_ELEMENT_ITEM_ID": "7001",
        "P_NAME": "\u9752\u7363\u306e\u722a",
        "8Cx57oAk": "\u9752\u7363\u306e\u722a",
        "P_RARE": "2",
        "P_DISPORDER": "7001",
        "CA7uXs6D": "99",
        "P_DISP_DICTIONARY": "0",
        "P_ICON_ID": "301",
        "60IsqxDt": "1",
        "o7e4HXMP": "1,1,0,1,0,0,0,0",
        "P_DOUBLE_SPHERE_TRIGGER": "0,0,0,0",
        "P_DICTIONARY_NO": "1",
        "P_DICTIONARY_BG": "31",
        "T04pJPmh": "",
        "P_NEED_SWITCH_INFO": "0",
        "P_HIDE_SWITCH_INFO": "0",
        "P_OPEN_SWITCH_INFO": "0"
    },
    {
        "P_ELEMENT_ITEM_ID": "7002",
        "P_NAME": "\u8d64\u7363\u306e\u722a",
        "8Cx57oAk": "\u8d64\u7363\u306e\u722a",
        "P_RARE": "3",
        "P_DISPORDER": "7002",
        "CA7uXs6D": "99",
        "P_DISP_DICTIONARY": "0",
        "P_ICON_ID": "304",
        "60IsqxDt": "1",
        "o7e4HXMP": "1,1,0,1,0,0,0,0",
        "P_DOUBLE_SPHERE_TRIGGER": "0,0,0,0",
        "P_DICTIONARY_NO": "1",
        "P_DICTIONARY_BG": "32",
        "T04pJPmh": "",
        "P_NEED_SWITCH_INFO": "0",
        "P_HIDE_SWITCH_INFO": "0",
        "P_OPEN_SWITCH_INFO": "0"
    },
    {
        "P_ELEMENT_ITEM_ID": "8000",
        "P_NAME": "\u7dd1\u7363\u306e\u7259",
        "8Cx57oAk": "\u7dd1\u7363\u306e\u7259",
        "P_RARE": "1",
        "P_DISPORDER": "8000",
        "CA7uXs6D": "99",
        "P_DISP_DICTIONARY": "0",
        "P_ICON_ID": "350",
        "60IsqxDt": "1",
        "o7e4HXMP": "1,1,0,1,0,0,0,0",
        "P_DOUBLE_SPHERE_TRIGGER": "0,0,0,0",
        "P_DICTIONARY_NO": "1",
        "P_DICTIONARY_BG": "33",
        "T04pJPmh": "",
        "P_NEED_SWITCH_INFO": "0",
        "P_HIDE_SWITCH_INFO": "0",
        "P_OPEN_SWITCH_INFO": "0"
    },
    {
        "P_ELEMENT_ITEM_ID": "8001",
        "P_NAME": "\u9752\u7363\u306e\u7259",
        "8Cx57oAk": "\u9752\u7363\u306e\u7259",
        "P_RARE": "2",
        "P_DISPORDER": "8001",
        "CA7uXs6D": "99",
        "P_DISP_DICTIONARY": "0",
        "P_ICON_ID": "351",
        "60IsqxDt": "1",
        "o7e4HXMP": "1,1,0,1,0,0,0,0",
        "P_DOUBLE_SPHERE_TRIGGER": "0,0,0,0",
        "P_DICTIONARY_NO": "1",
        "P_DICTIONARY_BG": "34",
        "T04pJPmh": "",
        "P_NEED_SWITCH_INFO": "0",
        "P_HIDE_SWITCH_INFO": "0",
        "P_OPEN_SWITCH_INFO": "0"
    },
    {
        "P_ELEMENT_ITEM_ID": "8002",
        "P_NAME": "\u8d64\u7363\u306e\u7259",
        "8Cx57oAk": "\u8d64\u7363\u306e\u7259",
        "P_RARE": "3",
        "P_DISPORDER": "8002",
        "CA7uXs6D": "99",
        "P_DISP_DICTIONARY": "0",
        "P_ICON_ID": "354",
        "60IsqxDt": "1",
        "o7e4HXMP": "1,1,0,1,0,0,0,0",
        "P_DOUBLE_SPHERE_TRIGGER": "0,0,0,0",
        "P_DICTIONARY_NO": "1",
        "P_DICTIONARY_BG": "35",
        "T04pJPmh": "",
        "P_NEED_SWITCH_INFO": "0",
        "P_HIDE_SWITCH_INFO": "0",
        "P_OPEN_SWITCH_INFO": "0"
    },
    {
        "P_ELEMENT_ITEM_ID": "9000",
        "P_NAME": "\u7fe0\u900f\u306e\u76ae",
        "8Cx57oAk": "\u7fe0\u900f\u306e\u76ae",
        "P_RARE": "1",
        "P_DISPORDER": "9000",
        "CA7uXs6D": "99",
        "P_DISP_DICTIONARY": "0",
        "P_ICON_ID": "450",
        "60IsqxDt": "1",
        "o7e4HXMP": "1,1,0,1,0,0,0,0",
        "P_DOUBLE_SPHERE_TRIGGER": "0,0,0,0",
        "P_DICTIONARY_NO": "1",
        "P_DICTIONARY_BG": "36",
        "T04pJPmh": "",
        "P_NEED_SWITCH_INFO": "0",
        "P_HIDE_SWITCH_INFO": "0",
        "P_OPEN_SWITCH_INFO": "0"
    },
    {
        "P_ELEMENT_ITEM_ID": "9001",
        "P_NAME": "\u7d3a\u78a7\u306e\u76ae",
        "8Cx57oAk": "\u7d3a\u78a7\u306e\u76ae",
        "P_RARE": "2",
        "P_DISPORDER": "9001",
        "CA7uXs6D": "99",
        "P_DISP_DICTIONARY": "0",
        "P_ICON_ID": "451",
        "60IsqxDt": "1",
        "o7e4HXMP": "1,1,0,1,0,0,0,0",
        "P_DOUBLE_SPHERE_TRIGGER": "0,0,0,0",
        "P_DICTIONARY_NO": "1",
        "P_DICTIONARY_BG": "37",
        "T04pJPmh": "",
        "P_NEED_SWITCH_INFO": "0",
        "P_HIDE_SWITCH_INFO": "0",
        "P_OPEN_SWITCH_INFO": "0"
    },
    {
        "P_ELEMENT_ITEM_ID": "9002",
        "P_NAME": "\u7dcb\u7c8b\u306e\u76ae",
        "8Cx57oAk": "\u7dcb\u7c8b\u306e\u76ae",
        "P_RARE": "3",
        "P_DISPORDER": "9002",
        "CA7uXs6D": "99",
        "P_DISP_DICTIONARY": "0",
        "P_ICON_ID": "454",
        "60IsqxDt": "1",
        "o7e4HXMP": "1,1,0,1,0,0,0,0",
        "P_DOUBLE_SPHERE_TRIGGER": "0,0,0,0",
        "P_DICTIONARY_NO": "1",
        "P_DICTIONARY_BG": "38",
        "T04pJPmh": "",
        "P_NEED_SWITCH_INFO": "0",
        "P_HIDE_SWITCH_INFO": "0",
        "P_OPEN_SWITCH_INFO": "0"
    },
    {
        "P_ELEMENT_ITEM_ID": "10000",
        "P_NAME": "\u30c6\u30aa\u306e\u7fbd",
        "8Cx57oAk": "\u30c6\u30aa\u306e\u7fbd",
        "P_RARE": "1",
        "P_DISPORDER": "10000",
        "CA7uXs6D": "99",
        "P_DISP_DICTIONARY": "0",
        "P_ICON_ID": "150",
        "60IsqxDt": "1",
        "o7e4HXMP": "1,1,0,1,0,0,0,0",
        "P_DOUBLE_SPHERE_TRIGGER": "0,0,0,0",
        "P_DICTIONARY_NO": "1",
        "P_DICTIONARY_BG": "39",
        "T04pJPmh": "",
        "P_NEED_SWITCH_INFO": "0",
        "P_HIDE_SWITCH_INFO": "0",
        "P_OPEN_SWITCH_INFO": "0"
    },
    {
        "P_ELEMENT_ITEM_ID": "10001",
        "P_NAME": "\u30b7\u30f3\u306e\u7fbd",
        "8Cx57oAk": "\u30b7\u30f3\u306e\u7fbd",
        "P_RARE": "2",
        "P_DISPORDER": "10001",
        "CA7uXs6D": "99",
        "P_DISP_DICTIONARY": "0",
        "P_ICON_ID": "151",
        "60IsqxDt": "1",
        "o7e4HXMP": "1,1,0,1,0,0,0,0",
        "P_DOUBLE_SPHERE_TRIGGER": "0,0,0,0",
        "P_DICTIONARY_NO": "1",
        "P_DICTIONARY_BG": "40",
        "T04pJPmh": "",
        "P_NEED_SWITCH_INFO": "0",
        "P_HIDE_SWITCH_INFO": "0",
        "P_OPEN_SWITCH_INFO": "0"
    },
    {
        "P_ELEMENT_ITEM_ID": "10002",
        "P_NAME": "\u30e9\u30a6\u306e\u7fbd",
        "8Cx57oAk": "\u30e9\u30a6\u306e\u7fbd",
        "P_RARE": "3",
        "P_DISPORDER": "10002",
        "CA7uXs6D": "99",
        "P_DISP_DICTIONARY": "0",
        "P_ICON_ID": "154",
        "60IsqxDt": "1",
        "o7e4HXMP": "1,1,0,1,0,0,0,0",
        "P_DOUBLE_SPHERE_TRIGGER": "0,0,0,0",
        "P_DICTIONARY_NO": "1",
        "P_DICTIONARY_BG": "41",
        "T04pJPmh": "",
        "P_NEED_SWITCH_INFO": "0",
        "P_HIDE_SWITCH_INFO": "0",
        "P_OPEN_SWITCH_INFO": "0"
    },
    {
        "P_ELEMENT_ITEM_ID": "11000",
        "P_NAME": "\u7dd1\u74e2\u866b",
        "8Cx57oAk": "\u7dd1\u74e2\u866b",
        "P_RARE": "1",
        "P_DISPORDER": "11000",
        "CA7uXs6D": "99",
        "P_DISP_DICTIONARY": "0",
        "P_ICON_ID": "600",
        "60IsqxDt": "1",
        "o7e4HXMP": "1,1,0,1,0,0,0,0",
        "P_DOUBLE_SPHERE_TRIGGER": "0,0,0,0",
        "P_DICTIONARY_NO": "1",
        "P_DICTIONARY_BG": "42",
        "T04pJPmh": "",
        "P_NEED_SWITCH_INFO": "0",
        "P_HIDE_SWITCH_INFO": "0",
        "P_OPEN_SWITCH_INFO": "0"
    },
    {
        "P_ELEMENT_ITEM_ID": "11001",
        "P_NAME": "\u9752\u74e2\u866b",
        "8Cx57oAk": "\u9752\u74e2\u866b",
        "P_RARE": "2",
        "P_DISPORDER": "11001",
        "CA7uXs6D": "99",
        "P_DISP_DICTIONARY": "0",
        "P_ICON_ID": "601",
        "60IsqxDt": "1",
        "o7e4HXMP": "1,1,0,1,0,0,0,0",
        "P_DOUBLE_SPHERE_TRIGGER": "0,0,0,0",
        "P_DICTIONARY_NO": "1",
        "P_DICTIONARY_BG": "43",
        "T04pJPmh": "",
        "P_NEED_SWITCH_INFO": "0",
        "P_HIDE_SWITCH_INFO": "0",
        "P_OPEN_SWITCH_INFO": "0"
    },
    {
        "P_ELEMENT_ITEM_ID": "11002",
        "P_NAME": "\u8d64\u74e2\u866b",
        "8Cx57oAk": "\u8d64\u74e2\u866b",
        "P_RARE": "3",
        "P_DISPORDER": "11002",
        "CA7uXs6D": "99",
        "P_DISP_DICTIONARY": "0",
        "P_ICON_ID": "604",
        "60IsqxDt": "1",
        "o7e4HXMP": "1,1,0,1,0,0,0,0",
        "P_DOUBLE_SPHERE_TRIGGER": "0,0,0,0",
        "P_DICTIONARY_NO": "1",
        "P_DICTIONARY_BG": "44",
        "T04pJPmh": "",
        "P_NEED_SWITCH_INFO": "0",
        "P_HIDE_SWITCH_INFO": "0",
        "P_OPEN_SWITCH_INFO": "0"
    },
    {
        "P_ELEMENT_ITEM_ID": "12000",
        "P_NAME": "\u5186\u66dc\u9271",
        "8Cx57oAk": "\u5186\u66dc\u9271",
        "P_RARE": "2",
        "P_DISPORDER": "13000",
        "CA7uXs6D": "99",
        "P_DISP_DICTIONARY": "0",
        "P_ICON_ID": "650",
        "60IsqxDt": "1",
        "o7e4HXMP": "1,1,0,1,0,1,0,0",
        "P_DOUBLE_SPHERE_TRIGGER": "0,0,0,0",
        "P_DICTIONARY_NO": "1",
        "P_DICTIONARY_BG": "45",
        "T04pJPmh": "",
        "P_NEED_SWITCH_INFO": "0",
        "P_HIDE_SWITCH_INFO": "0",
        "P_OPEN_SWITCH_INFO": "0"
    },
    {
        "P_ELEMENT_ITEM_ID": "12001",
        "P_NAME": "\u84bc\u73ca\u9271",
        "8Cx57oAk": "\u84bc\u73ca\u9271",
        "P_RARE": "3",
        "P_DISPORDER": "13001",
        "CA7uXs6D": "99",
        "P_DISP_DICTIONARY": "0",
        "P_ICON_ID": "651",
        "60IsqxDt": "1",
        "o7e4HXMP": "1,1,0,1,0,1,0,0",
        "P_DOUBLE_SPHERE_TRIGGER": "0,0,0,0",
        "P_DICTIONARY_NO": "1",
        "P_DICTIONARY_BG": "46",
        "T04pJPmh": "",
        "P_NEED_SWITCH_INFO": "0",
        "P_HIDE_SWITCH_INFO": "0",
        "P_OPEN_SWITCH_INFO": "0"
    },
    {
        "P_ELEMENT_ITEM_ID": "13000",
        "P_NAME": "\u525b\u7f85\u7d17",
        "8Cx57oAk": "\u525b\u7f85\u7d17",
        "P_RARE": "2",
        "P_DISPORDER": "14000",
        "CA7uXs6D": "99",
        "P_DISP_DICTIONARY": "0",
        "P_ICON_ID": "700",
        "60IsqxDt": "1",
        "o7e4HXMP": "1,1,0,1,0,1,0,0",
        "P_DOUBLE_SPHERE_TRIGGER": "0,0,0,0",
        "P_DICTIONARY_NO": "1",
        "P_DICTIONARY_BG": "47",
        "T04pJPmh": "",
        "P_NEED_SWITCH_INFO": "0",
        "P_HIDE_SWITCH_INFO": "0",
        "P_OPEN_SWITCH_INFO": "0"
    },
    {
        "P_ELEMENT_ITEM_ID": "13001",
        "P_NAME": "\u5343\u7e54\u5e03",
        "8Cx57oAk": "\u5343\u7e54\u5e03",
        "P_RARE": "3",
        "P_DISPORDER": "14001",
        "CA7uXs6D": "99",
        "P_DISP_DICTIONARY": "0",
        "P_ICON_ID": "701",
        "60IsqxDt": "1",
        "o7e4HXMP": "1,1,0,1,0,1,0,0",
        "P_DOUBLE_SPHERE_TRIGGER": "0,0,0,0",
        "P_DICTIONARY_NO": "1",
        "P_DICTIONARY_BG": "48",
        "T04pJPmh": "",
        "P_NEED_SWITCH_INFO": "0",
        "P_HIDE_SWITCH_INFO": "0",
        "P_OPEN_SWITCH_INFO": "0"
    },
    {
        "P_ELEMENT_ITEM_ID": "14000",
        "P_NAME": "\u30b5\u30af\u6750",
        "8Cx57oAk": "\u30b5\u30af\u6750",
        "P_RARE": "2",
        "P_DISPORDER": "15000",
        "CA7uXs6D": "99",
        "P_DISP_DICTIONARY": "0",
        "P_ICON_ID": "750",
        "60IsqxDt": "1",
        "o7e4HXMP": "1,1,0,1,0,1,0,0",
        "P_DOUBLE_SPHERE_TRIGGER": "0,0,0,0",
        "P_DICTIONARY_NO": "1",
        "P_DICTIONARY_BG": "49",
        "T04pJPmh": "",
        "P_NEED_SWITCH_INFO": "0",
        "P_HIDE_SWITCH_INFO": "0",
        "P_OPEN_SWITCH_INFO": "0"
    },
    {
        "P_ELEMENT_ITEM_ID": "14001",
        "P_NAME": "\u30d0\u30cf\u6750",
        "8Cx57oAk": "\u30d0\u30cf\u6750",
        "P_RARE": "3",
        "P_DISPORDER": "15001",
        "CA7uXs6D": "99",
        "P_DISP_DICTIONARY": "0",
        "P_ICON_ID": "751",
        "60IsqxDt": "1",
        "o7e4HXMP": "1,1,0,1,0,1,0,0",
        "P_DOUBLE_SPHERE_TRIGGER": "0,0,0,0",
        "P_DICTIONARY_NO": "1",
        "P_DICTIONARY_BG": "50",
        "T04pJPmh": "",
        "P_NEED_SWITCH_INFO": "0",
        "P_HIDE_SWITCH_INFO": "0",
        "P_OPEN_SWITCH_INFO": "0"
    },
    {
        "P_ELEMENT_ITEM_ID": "15000",
        "P_NAME": "\u6ce2\u52d5\u7d50\u6676",
        "8Cx57oAk": "\u6ce2\u52d5\u7d50\u6676",
        "P_RARE": "4",
        "P_DISPORDER": "16000",
        "CA7uXs6D": "99",
        "P_DISP_DICTIONARY": "1",
        "P_ICON_ID": "800",
        "60IsqxDt": "1",
        "o7e4HXMP": "1,1,0,1,0,1,0,0",
        "P_DOUBLE_SPHERE_TRIGGER": "0,0,0,0",
        "P_DICTIONARY_NO": "1",
        "P_DICTIONARY_BG": "51",
        "T04pJPmh": "",
        "P_NEED_SWITCH_INFO": "0",
        "P_HIDE_SWITCH_INFO": "0",
        "P_OPEN_SWITCH_INFO": "0"
    },
    {
        "P_ELEMENT_ITEM_ID": "15001",
        "P_NAME": "\u7149\u5a01\u7d50\u6676",
        "8Cx57oAk": "\u7149\u5a01\u7d50\u6676",
        "P_RARE": "5",
        "P_DISPORDER": "16001",
        "CA7uXs6D": "99",
        "P_DISP_DICTIONARY": "1",
        "P_ICON_ID": "801",
        "60IsqxDt": "1",
        "o7e4HXMP": "1,1,0,1,0,1,0,0",
        "P_DOUBLE_SPHERE_TRIGGER": "0,0,0,0",
        "P_DICTIONARY_NO": "1",
        "P_DICTIONARY_BG": "52",
        "T04pJPmh": "",
        "P_NEED_SWITCH_INFO": "0",
        "P_HIDE_SWITCH_INFO": "0",
        "P_OPEN_SWITCH_INFO": "0"
    },
    {
        "P_ELEMENT_ITEM_ID": "16000",
        "P_NAME": "\u30ac\u30eb\u306e\u8089",
        "8Cx57oAk": "\u30ac\u30eb\u306e\u8089",
        "P_RARE": "1",
        "P_DISPORDER": "12000",
        "CA7uXs6D": "99",
        "P_DISP_DICTIONARY": "0",
        "P_ICON_ID": "852",
        "60IsqxDt": "1",
        "o7e4HXMP": "1,0,0,0,0,0,0,0",
        "P_DOUBLE_SPHERE_TRIGGER": "0,0,0,0",
        "P_DICTIONARY_NO": "1",
        "P_DICTIONARY_BG": "53",
        "T04pJPmh": "",
        "P_NEED_SWITCH_INFO": "0",
        "P_HIDE_SWITCH_INFO": "0",
        "P_OPEN_SWITCH_INFO": "0"
    },
    {
        "P_ELEMENT_ITEM_ID": "16001",
        "P_NAME": "\u30c6\u30b0\u306e\u8089",
        "8Cx57oAk": "\u30c6\u30b0\u306e\u8089",
        "P_RARE": "2",
        "P_DISPORDER": "12001",
        "CA7uXs6D": "99",
        "P_DISP_DICTIONARY": "0",
        "P_ICON_ID": "851",
        "60IsqxDt": "1",
        "o7e4HXMP": "1,0,0,0,0,0,0,0",
        "P_DOUBLE_SPHERE_TRIGGER": "0,0,0,0",
        "P_DICTIONARY_NO": "1",
        "P_DICTIONARY_BG": "54",
        "T04pJPmh": "",
        "P_NEED_SWITCH_INFO": "0",
        "P_HIDE_SWITCH_INFO": "0",
        "P_OPEN_SWITCH_INFO": "0"
    },
    {
        "P_ELEMENT_ITEM_ID": "20000",
        "P_NAME": "\u661f\u796d\u8349",
        "8Cx57oAk": "\u661f\u796d\u8349",
        "P_RARE": "3",
        "P_DISPORDER": "20000",
        "CA7uXs6D": "99",
        "P_DISP_DICTIONARY": "0",
        "P_ICON_ID": "105",
        "60IsqxDt": "1",
        "o7e4HXMP": "0,0,0,1,0,0,0,0",
        "P_DOUBLE_SPHERE_TRIGGER": "0,0,0,0",
        "P_DICTIONARY_NO": "1",
        "P_DICTIONARY_BG": "56",
        "T04pJPmh": "",
        "P_NEED_SWITCH_INFO": "0",
        "P_HIDE_SWITCH_INFO": "0",
        "P_OPEN_SWITCH_INFO": "0"
    },
    {
        "P_ELEMENT_ITEM_ID": "20001",
        "P_NAME": "\u30b8\u30b0\u306e\u5b9f",
        "8Cx57oAk": "\u30b8\u30b0\u306e\u5b9f",
        "P_RARE": "3",
        "P_DISPORDER": "20001",
        "CA7uXs6D": "99",
        "P_DISP_DICTIONARY": "0",
        "P_ICON_ID": "205",
        "60IsqxDt": "1",
        "o7e4HXMP": "0,0,0,1,0,0,0,0",
        "P_DOUBLE_SPHERE_TRIGGER": "0,0,0,0",
        "P_DICTIONARY_NO": "1",
        "P_DICTIONARY_BG": "57",
        "T04pJPmh": "",
        "P_NEED_SWITCH_INFO": "0",
        "P_HIDE_SWITCH_INFO": "0",
        "P_OPEN_SWITCH_INFO": "0"
    },
    {
        "P_ELEMENT_ITEM_ID": "20002",
        "P_NAME": "\u83ef\u6ec5\u306e\u773c",
        "8Cx57oAk": "\u83ef\u6ec5\u306e\u773c",
        "P_RARE": "3",
        "P_DISPORDER": "20002",
        "CA7uXs6D": "99",
        "P_DISP_DICTIONARY": "0",
        "P_ICON_ID": "405",
        "60IsqxDt": "1",
        "o7e4HXMP": "0,0,0,1,0,0,0,0",
        "P_DOUBLE_SPHERE_TRIGGER": "0,0,0,0",
        "P_DICTIONARY_NO": "1",
        "P_DICTIONARY_BG": "58",
        "T04pJPmh": "",
        "P_NEED_SWITCH_INFO": "0",
        "P_HIDE_SWITCH_INFO": "0",
        "P_OPEN_SWITCH_INFO": "0"
    },
    {
        "P_ELEMENT_ITEM_ID": "20003",
        "P_NAME": "\u6708\u967d\u306e\u96eb",
        "8Cx57oAk": "\u6708\u967d\u306e\u96eb",
        "P_RARE": "3",
        "P_DISPORDER": "20003",
        "CA7uXs6D": "99",
        "P_DISP_DICTIONARY": "0",
        "P_ICON_ID": "255",
        "60IsqxDt": "1",
        "o7e4HXMP": "0,0,0,1,0,0,0,0",
        "P_DOUBLE_SPHERE_TRIGGER": "0,0,0,0",
        "P_DICTIONARY_NO": "1",
        "P_DICTIONARY_BG": "59",
        "T04pJPmh": "",
        "P_NEED_SWITCH_INFO": "0",
        "P_HIDE_SWITCH_INFO": "0",
        "P_OPEN_SWITCH_INFO": "0"
    },
    {
        "P_ELEMENT_ITEM_ID": "20004",
        "P_NAME": "\u546a\u970a\u7940\u9aa8",
        "8Cx57oAk": "\u546a\u970a\u7940\u9aa8",
        "P_RARE": "3",
        "P_DISPORDER": "20004",
        "CA7uXs6D": "99",
        "P_DISP_DICTIONARY": "0",
        "P_ICON_ID": "505",
        "60IsqxDt": "1",
        "o7e4HXMP": "0,0,0,1,0,0,0,0",
        "P_DOUBLE_SPHERE_TRIGGER": "0,0,0,0",
        "P_DICTIONARY_NO": "1",
        "P_DICTIONARY_BG": "60",
        "T04pJPmh": "",
        "P_NEED_SWITCH_INFO": "0",
        "P_HIDE_SWITCH_INFO": "0",
        "P_OPEN_SWITCH_INFO": "0"
    },
    {
        "P_ELEMENT_ITEM_ID": "20005",
        "P_NAME": "\u8056\u523b\u5fa1\u77f3",
        "8Cx57oAk": "\u8056\u523b\u5fa1\u77f3",
        "P_RARE": "3",
        "P_DISPORDER": "20005",
        "CA7uXs6D": "99",
        "P_DISP_DICTIONARY": "0",
        "P_ICON_ID": "555",
        "60IsqxDt": "1",
        "o7e4HXMP": "0,0,0,1,0,0,0,0",
        "P_DOUBLE_SPHERE_TRIGGER": "0,0,0,0",
        "P_DICTIONARY_NO": "1",
        "P_DICTIONARY_BG": "61",
        "T04pJPmh": "",
        "P_NEED_SWITCH_INFO": "0",
        "P_HIDE_SWITCH_INFO": "0",
        "P_OPEN_SWITCH_INFO": "0"
    },
    {
        "P_ELEMENT_ITEM_ID": "20006",
        "P_NAME": "\u30b4\u30a6\u306e\u7fbd",
        "8Cx57oAk": "\u30b4\u30a6\u306e\u7fbd",
        "P_RARE": "3",
        "P_DISPORDER": "20006",
        "CA7uXs6D": "99",
        "P_DISP_DICTIONARY": "0",
        "P_ICON_ID": "155",
        "60IsqxDt": "1",
        "o7e4HXMP": "0,0,0,1,0,0,0,0",
        "P_DOUBLE_SPHERE_TRIGGER": "0,0,0,0",
        "P_DICTIONARY_NO": "1",
        "P_DICTIONARY_BG": "62",
        "T04pJPmh": "",
        "P_NEED_SWITCH_INFO": "0",
        "P_HIDE_SWITCH_INFO": "0",
        "P_OPEN_SWITCH_INFO": "0"
    },
    {
        "P_ELEMENT_ITEM_ID": "20007",
        "P_NAME": "\u5e7b\u7d2b\u306e\u76ae",
        "8Cx57oAk": "\u5e7b\u7d2b\u306e\u76ae",
        "P_RARE": "3",
        "P_DISPORDER": "20007",
        "CA7uXs6D": "99",
        "P_DISP_DICTIONARY": "0",
        "P_ICON_ID": "455",
        "60IsqxDt": "1",
        "o7e4HXMP": "0,0,0,1,0,0,0,0",
        "P_DOUBLE_SPHERE_TRIGGER": "0,0,0,0",
        "P_DICTIONARY_NO": "1",
        "P_DICTIONARY_BG": "64",
        "T04pJPmh": "",
        "P_NEED_SWITCH_INFO": "0",
        "P_HIDE_SWITCH_INFO": "0",
        "P_OPEN_SWITCH_INFO": "0"
    },
    {
        "P_ELEMENT_ITEM_ID": "20008",
        "P_NAME": "\u523b\u547d\u88c2\u722a",
        "8Cx57oAk": "\u523b\u547d\u88c2\u722a",
        "P_RARE": "3",
        "P_DISPORDER": "20008",
        "CA7uXs6D": "99",
        "P_DISP_DICTIONARY": "0",
        "P_ICON_ID": "305",
        "60IsqxDt": "1",
        "o7e4HXMP": "0,0,0,1,0,0,0,0",
        "P_DOUBLE_SPHERE_TRIGGER": "0,0,0,0",
        "P_DICTIONARY_NO": "1",
        "P_DICTIONARY_BG": "65",
        "T04pJPmh": "",
        "P_NEED_SWITCH_INFO": "0",
        "P_HIDE_SWITCH_INFO": "0",
        "P_OPEN_SWITCH_INFO": "0"
    },
    {
        "P_ELEMENT_ITEM_ID": "20009",
        "P_NAME": "\u8cb4\u7d2b\u866b",
        "8Cx57oAk": "\u8cb4\u7d2b\u866b",
        "P_RARE": "3",
        "P_DISPORDER": "20009",
        "CA7uXs6D": "99",
        "P_DISP_DICTIONARY": "0",
        "P_ICON_ID": "605",
        "60IsqxDt": "1",
        "o7e4HXMP": "0,0,0,1,0,0,0,0",
        "P_DOUBLE_SPHERE_TRIGGER": "0,0,0,0",
        "P_DICTIONARY_NO": "1",
        "P_DICTIONARY_BG": "66",
        "T04pJPmh": "",
        "P_NEED_SWITCH_INFO": "0",
        "P_HIDE_SWITCH_INFO": "0",
        "P_OPEN_SWITCH_INFO": "0"
    },
    {
        "P_ELEMENT_ITEM_ID": "20010",
        "P_NAME": "\u9b54\u8755\u9ed2\u6a80",
        "8Cx57oAk": "\u9b54\u8755\u9ed2\u6a80",
        "P_RARE": "3",
        "P_DISPORDER": "20010",
        "CA7uXs6D": "99",
        "P_DISP_DICTIONARY": "0",
        "P_ICON_ID": "755",
        "60IsqxDt": "1",
        "o7e4HXMP": "0,0,0,1,0,0,0,0",
        "P_DOUBLE_SPHERE_TRIGGER": "0,0,0,0",
        "P_DICTIONARY_NO": "1",
        "P_DICTIONARY_BG": "67",
        "T04pJPmh": "",
        "P_NEED_SWITCH_INFO": "0",
        "P_HIDE_SWITCH_INFO": "0",
        "P_OPEN_SWITCH_INFO": "0"
    },
    {
        "P_ELEMENT_ITEM_ID": "20011",
        "P_NAME": "\u5929\u71d0\u9aa8",
        "8Cx57oAk": "\u5929\u71d0\u9aa8",
        "P_RARE": "3",
        "P_DISPORDER": "20011",
        "CA7uXs6D": "99",
        "P_DISP_DICTIONARY": "0",
        "P_ICON_ID": "503",
        "60IsqxDt": "1",
        "o7e4HXMP": "0,0,0,1,0,0,0,0",
        "P_DOUBLE_SPHERE_TRIGGER": "0,0,0,0",
        "P_DICTIONARY_NO": "1",
        "P_DICTIONARY_BG": "68",
        "T04pJPmh": "",
        "P_NEED_SWITCH_INFO": "0",
        "P_HIDE_SWITCH_INFO": "0",
        "P_OPEN_SWITCH_INFO": "0"
    },
    {
        "P_ELEMENT_ITEM_ID": "20012",
        "P_NAME": "\u9ec4\u8f1d\u5343\u71e6\u722a",
        "8Cx57oAk": "\u8f1d\u71e6\u722a",
        "P_RARE": "4",
        "P_DISPORDER": "20012",
        "CA7uXs6D": "99",
        "P_DISP_DICTIONARY": "0",
        "P_ICON_ID": "302",
        "60IsqxDt": "1",
        "o7e4HXMP": "0,0,0,1,0,0,0,0",
        "P_DOUBLE_SPHERE_TRIGGER": "0,0,0,0",
        "P_DICTIONARY_NO": "1",
        "P_DICTIONARY_BG": "69",
        "T04pJPmh": "",
        "P_NEED_SWITCH_INFO": "0",
        "P_HIDE_SWITCH_INFO": "0",
        "P_OPEN_SWITCH_INFO": "0"
    },
    {
        "P_ELEMENT_ITEM_ID": "20013",
        "P_NAME": "\u5bb5\u95c7\u7e7b\u5b50",
        "8Cx57oAk": "\u5bb5\u95c7\u7e7b\u5b50",
        "P_RARE": "3",
        "P_DISPORDER": "20013",
        "CA7uXs6D": "99",
        "P_DISP_DICTIONARY": "0",
        "P_ICON_ID": "705",
        "60IsqxDt": "1",
        "o7e4HXMP": "0,0,0,1,0,0,0,0",
        "P_DOUBLE_SPHERE_TRIGGER": "0,0,0,0",
        "P_DICTIONARY_NO": "1",
        "P_DICTIONARY_BG": "70",
        "T04pJPmh": "",
        "P_NEED_SWITCH_INFO": "0",
        "P_HIDE_SWITCH_INFO": "0",
        "P_OPEN_SWITCH_INFO": "0"
    },
    {
        "P_ELEMENT_ITEM_ID": "20014",
        "P_NAME": "\u5f37\u6b32\u306e\u8f1d\u9aa8",
        "8Cx57oAk": "\u5f37\u6b32\u8f1d\u9aa8",
        "P_RARE": "4",
        "P_DISPORDER": "20014",
        "CA7uXs6D": "99",
        "P_DISP_DICTIONARY": "0",
        "P_ICON_ID": "502",
        "60IsqxDt": "1",
        "o7e4HXMP": "0,0,0,1,0,0,0,0",
        "P_DOUBLE_SPHERE_TRIGGER": "0,0,0,0",
        "P_DICTIONARY_NO": "1",
        "P_DICTIONARY_BG": "71",
        "T04pJPmh": "",
        "P_NEED_SWITCH_INFO": "0",
        "P_HIDE_SWITCH_INFO": "0",
        "P_OPEN_SWITCH_INFO": "0"
    },
    {
        "P_ELEMENT_ITEM_ID": "20015",
        "P_NAME": "\u5cfb\u92ed\u60aa\u7259",
        "8Cx57oAk": "\u5cfb\u92ed\u60aa\u7259",
        "P_RARE": "3",
        "P_DISPORDER": "20015",
        "CA7uXs6D": "99",
        "P_DISP_DICTIONARY": "0",
        "P_ICON_ID": "355",
        "60IsqxDt": "1",
        "o7e4HXMP": "0,0,0,1,0,0,0,0",
        "P_DOUBLE_SPHERE_TRIGGER": "0,0,0,0",
        "P_DICTIONARY_NO": "1",
        "P_DICTIONARY_BG": "73",
        "T04pJPmh": "",
        "P_NEED_SWITCH_INFO": "0",
        "P_HIDE_SWITCH_INFO": "0",
        "P_OPEN_SWITCH_INFO": "0"
    },
    {
        "P_ELEMENT_ITEM_ID": "20016",
        "P_NAME": "\u91d1\u7cf8\u5929\u9d5e\u7d68",
        "8Cx57oAk": "\u91d1\u7cf8\u7d68",
        "P_RARE": "4",
        "P_DISPORDER": "20016",
        "CA7uXs6D": "99",
        "P_DISP_DICTIONARY": "0",
        "P_ICON_ID": "702",
        "60IsqxDt": "1",
        "o7e4HXMP": "0,0,0,1,0,0,0,0",
        "P_DOUBLE_SPHERE_TRIGGER": "0,0,0,0",
        "P_DICTIONARY_NO": "1",
        "P_DICTIONARY_BG": "74",
        "T04pJPmh": "",
        "P_NEED_SWITCH_INFO": "0",
        "P_HIDE_SWITCH_INFO": "0",
        "P_OPEN_SWITCH_INFO": "0"
    },
    {
        "P_ELEMENT_ITEM_ID": "20017",
        "P_NAME": "\u9b42\u907a\u7d50\u6676",
        "8Cx57oAk": "\u9b42\u907a\u7d50\u6676",
        "P_RARE": "3",
        "P_DISPORDER": "20017",
        "CA7uXs6D": "99",
        "P_DISP_DICTIONARY": "0",
        "P_ICON_ID": "803",
        "60IsqxDt": "1",
        "o7e4HXMP": "0,0,0,1,0,0,0,0",
        "P_DOUBLE_SPHERE_TRIGGER": "0,0,0,0",
        "P_DICTIONARY_NO": "1",
        "P_DICTIONARY_BG": "75",
        "T04pJPmh": "",
        "P_NEED_SWITCH_INFO": "0",
        "P_HIDE_SWITCH_INFO": "0",
        "P_OPEN_SWITCH_INFO": "0"
    },
    {
        "P_ELEMENT_ITEM_ID": "20018",
        "P_NAME": "\u7dcb\u5fc3\u7d50\u6676",
        "8Cx57oAk": "\u7dcb\u5fc3\u7d50\u6676",
        "P_RARE": "5",
        "P_DISPORDER": "20018",
        "CA7uXs6D": "99",
        "P_DISP_DICTIONARY": "0",
        "P_ICON_ID": "804",
        "60IsqxDt": "1",
        "o7e4HXMP": "0,0,0,1,0,0,0,0",
        "P_DOUBLE_SPHERE_TRIGGER": "0,0,0,0",
        "P_DICTIONARY_NO": "1",
        "P_DICTIONARY_BG": "76",
        "T04pJPmh": "",
        "P_NEED_SWITCH_INFO": "0",
        "P_HIDE_SWITCH_INFO": "0",
        "P_OPEN_SWITCH_INFO": "0"
    },
    {
        "P_ELEMENT_ITEM_ID": "20019",
        "P_NAME": "\u771f\u9855\u9271",
        "8Cx57oAk": "\u771f\u9855\u9271",
        "P_RARE": "3",
        "P_DISPORDER": "20019",
        "CA7uXs6D": "99",
        "P_DISP_DICTIONARY": "0",
        "P_ICON_ID": "656",
        "60IsqxDt": "1",
        "o7e4HXMP": "0,0,0,1,0,0,0,0",
        "P_DOUBLE_SPHERE_TRIGGER": "0,0,0,0",
        "P_DICTIONARY_NO": "1",
        "P_DICTIONARY_BG": "77",
        "T04pJPmh": "",
        "P_NEED_SWITCH_INFO": "0",
        "P_HIDE_SWITCH_INFO": "0",
        "P_OPEN_SWITCH_INFO": "0"
    },
    {
        "P_ELEMENT_ITEM_ID": "20020",
        "P_NAME": "\u721b\u6fb1\u9271",
        "8Cx57oAk": "\u721b\u6fb1\u9271",
        "P_RARE": "4",
        "P_DISPORDER": "20020",
        "CA7uXs6D": "99",
        "P_DISP_DICTIONARY": "0",
        "P_ICON_ID": "652",
        "60IsqxDt": "1",
        "o7e4HXMP": "0,0,0,1,0,0,0,0",
        "P_DOUBLE_SPHERE_TRIGGER": "0,0,0,0",
        "P_DICTIONARY_NO": "1",
        "P_DICTIONARY_BG": "78",
        "T04pJPmh": "",
        "P_NEED_SWITCH_INFO": "0",
        "P_HIDE_SWITCH_INFO": "0",
        "P_OPEN_SWITCH_INFO": "0"
    },
    {
        "P_ELEMENT_ITEM_ID": "20021",
        "P_NAME": "\u6697\u78e8\u5ca9",
        "8Cx57oAk": "\u6697\u78e8\u5ca9",
        "P_RARE": "3",
        "P_DISPORDER": "20021",
        "CA7uXs6D": "99",
        "P_DISP_DICTIONARY": "0",
        "P_ICON_ID": "556",
        "60IsqxDt": "1",
        "o7e4HXMP": "0,0,0,1,0,0,0,0",
        "P_DOUBLE_SPHERE_TRIGGER": "0,0,0,0",
        "P_DICTIONARY_NO": "1",
        "P_DICTIONARY_BG": "79",
        "T04pJPmh": "",
        "P_NEED_SWITCH_INFO": "0",
        "P_HIDE_SWITCH_INFO": "0",
        "P_OPEN_SWITCH_INFO": "0"
    },
    {
        "P_ELEMENT_ITEM_ID": "20022",
        "P_NAME": "\u5236\u70c8\u5ca9",
        "8Cx57oAk": "\u5236\u70c8\u5ca9",
        "P_RARE": "4",
        "P_DISPORDER": "20022",
        "CA7uXs6D": "99",
        "P_DISP_DICTIONARY": "0",
        "P_ICON_ID": "552",
        "60IsqxDt": "1",
        "o7e4HXMP": "0,0,0,1,0,0,0,0",
        "P_DOUBLE_SPHERE_TRIGGER": "0,0,0,0",
        "P_DICTIONARY_NO": "1",
        "P_DICTIONARY_BG": "80",
        "T04pJPmh": "",
        "P_NEED_SWITCH_INFO": "0",
        "P_HIDE_SWITCH_INFO": "0",
        "P_OPEN_SWITCH_INFO": "0"
    },
    {
        "P_ELEMENT_ITEM_ID": "20023",
        "P_NAME": "\u4e38\u93e1\u77f3",
        "8Cx57oAk": "\u4e38\u93e1\u77f3",
        "P_RARE": "3",
        "P_DISPORDER": "20023",
        "CA7uXs6D": "99",
        "P_DISP_DICTIONARY": "0",
        "P_ICON_ID": "406",
        "60IsqxDt": "1",
        "o7e4HXMP": "0,0,0,1,0,0,0,0",
        "P_DOUBLE_SPHERE_TRIGGER": "0,0,0,0",
        "P_DICTIONARY_NO": "1",
        "P_DICTIONARY_BG": "81",
        "T04pJPmh": "",
        "P_NEED_SWITCH_INFO": "0",
        "P_HIDE_SWITCH_INFO": "0",
        "P_OPEN_SWITCH_INFO": "0"
    },
    {
        "P_ELEMENT_ITEM_ID": "20024",
        "P_NAME": "\u8d70\u5bff\u77f3",
        "8Cx57oAk": "\u8d70\u5bff\u77f3",
        "P_RARE": "4",
        "P_DISPORDER": "20024",
        "CA7uXs6D": "99",
        "P_DISP_DICTIONARY": "0",
        "P_ICON_ID": "402",
        "60IsqxDt": "1",
        "o7e4HXMP": "0,0,0,1,0,0,0,0",
        "P_DOUBLE_SPHERE_TRIGGER": "0,0,0,0",
        "P_DICTIONARY_NO": "1",
        "P_DICTIONARY_BG": "82",
        "T04pJPmh": "",
        "P_NEED_SWITCH_INFO": "0",
        "P_HIDE_SWITCH_INFO": "0",
        "P_OPEN_SWITCH_INFO": "0"
    },
    {
        "P_ELEMENT_ITEM_ID": "20025",
        "P_NAME": "\u5f81\u5a01\u7d50\u6676",
        "8Cx57oAk": "\u5f81\u5a01\u7d50\u6676",
        "P_RARE": "4",
        "P_DISPORDER": "20025",
        "CA7uXs6D": "99",
        "P_DISP_DICTIONARY": "0",
        "P_ICON_ID": "801",
        "60IsqxDt": "1",
        "o7e4HXMP": "0,0,0,1,0,0,0,0",
        "P_DOUBLE_SPHERE_TRIGGER": "0,0,0,0",
        "P_DICTIONARY_NO": "1",
        "P_DICTIONARY_BG": "84",
        "T04pJPmh": "",
        "P_NEED_SWITCH_INFO": "0",
        "P_HIDE_SWITCH_INFO": "0",
        "P_OPEN_SWITCH_INFO": "0"
    },
    {
        "P_ELEMENT_ITEM_ID": "20026",
        "P_NAME": "\u7fd4\u51cc\u9271",
        "8Cx57oAk": "\u7fd4\u51cc\u9271",
        "P_RARE": "4",
        "P_DISPORDER": "20026",
        "CA7uXs6D": "99",
        "P_DISP_DICTIONARY": "0",
        "P_ICON_ID": "651",
        "60IsqxDt": "1",
        "o7e4HXMP": "0,0,0,1,0,0,0,0",
        "P_DOUBLE_SPHERE_TRIGGER": "0,0,0,0",
        "P_DICTIONARY_NO": "1",
        "P_DICTIONARY_BG": "85",
        "T04pJPmh": "",
        "P_NEED_SWITCH_INFO": "0",
        "P_HIDE_SWITCH_INFO": "0",
        "P_OPEN_SWITCH_INFO": "0"
    },
    {
        "P_ELEMENT_ITEM_ID": "20027",
        "P_NAME": "\u8352\u6563\u5ca9",
        "8Cx57oAk": "\u8352\u6563\u5ca9",
        "P_RARE": "4",
        "P_DISPORDER": "20027",
        "CA7uXs6D": "99",
        "P_DISP_DICTIONARY": "0",
        "P_ICON_ID": "551",
        "60IsqxDt": "1",
        "o7e4HXMP": "0,0,0,1,0,0,0,0",
        "P_DOUBLE_SPHERE_TRIGGER": "0,0,0,0",
        "P_DICTIONARY_NO": "1",
        "P_DICTIONARY_BG": "86",
        "T04pJPmh": "",
        "P_NEED_SWITCH_INFO": "0",
        "P_HIDE_SWITCH_INFO": "0",
        "P_OPEN_SWITCH_INFO": "0"
    },
    {
        "P_ELEMENT_ITEM_ID": "20028",
        "P_NAME": "\u5553\u660e\u77f3",
        "8Cx57oAk": "\u5553\u660e\u77f3",
        "P_RARE": "4",
        "P_DISPORDER": "20028",
        "CA7uXs6D": "99",
        "P_DISP_DICTIONARY": "0",
        "P_ICON_ID": "401",
        "60IsqxDt": "1",
        "o7e4HXMP": "0,0,0,1,0,0,0,0",
        "P_DOUBLE_SPHERE_TRIGGER": "0,0,0,0",
        "P_DICTIONARY_NO": "1",
        "P_DICTIONARY_BG": "87",
        "T04pJPmh": "",
        "P_NEED_SWITCH_INFO": "0",
        "P_HIDE_SWITCH_INFO": "0",
        "P_OPEN_SWITCH_INFO": "0"
    },
    {
        "P_ELEMENT_ITEM_ID": "20029",
        "P_NAME": "\u6df1\u5965\u4ec4\u5149",
        "8Cx57oAk": "\u6df1\u5965\u4ec4\u5149",
        "P_RARE": "3",
        "P_DISPORDER": "20029",
        "CA7uXs6D": "99",
        "P_DISP_DICTIONARY": "0",
        "P_ICON_ID": "655",
        "60IsqxDt": "1",
        "o7e4HXMP": "0,0,0,1,0,0,0,0",
        "P_DOUBLE_SPHERE_TRIGGER": "0,0,0,0",
        "P_DICTIONARY_NO": "1",
        "P_DICTIONARY_BG": "88",
        "T04pJPmh": "",
        "P_NEED_SWITCH_INFO": "0",
        "P_HIDE_SWITCH_INFO": "0",
        "P_OPEN_SWITCH_INFO": "0"
    },
    {
        "P_ELEMENT_ITEM_ID": "20030",
        "P_NAME": "\u738b\u9f8d\u306e\u7259",
        "8Cx57oAk": "\u738b\u9f8d\u306e\u7259",
        "P_RARE": "4",
        "P_DISPORDER": "20030",
        "CA7uXs6D": "99",
        "P_DISP_DICTIONARY": "0",
        "P_ICON_ID": "352",
        "60IsqxDt": "1",
        "o7e4HXMP": "0,0,0,1,0,0,0,0",
        "P_DOUBLE_SPHERE_TRIGGER": "0,0,0,0",
        "P_DICTIONARY_NO": "1",
        "P_DICTIONARY_BG": "89",
        "T04pJPmh": "",
        "P_NEED_SWITCH_INFO": "0",
        "P_HIDE_SWITCH_INFO": "0",
        "P_OPEN_SWITCH_INFO": "0"
    },
    {
        "P_ELEMENT_ITEM_ID": "20031",
        "P_NAME": "\u795e\u754f\u7d50\u6676",
        "8Cx57oAk": "\u795e\u754f\u7d50\u6676",
        "P_RARE": "4",
        "P_DISPORDER": "20031",
        "CA7uXs6D": "99",
        "P_DISP_DICTIONARY": "0",
        "P_ICON_ID": "806",
        "60IsqxDt": "1",
        "o7e4HXMP": "0,0,0,1,0,0,0,0",
        "P_DOUBLE_SPHERE_TRIGGER": "0,0,0,0",
        "P_DICTIONARY_NO": "1",
        "P_DICTIONARY_BG": "90",
        "T04pJPmh": "",
        "P_NEED_SWITCH_INFO": "0",
        "P_HIDE_SWITCH_INFO": "0",
        "P_OPEN_SWITCH_INFO": "0"
    },
    {
        "P_ELEMENT_ITEM_ID": "20032",
        "P_NAME": "\u958b\u95e2\u9271",
        "8Cx57oAk": "\u958b\u95e2\u9271",
        "P_RARE": "4",
        "P_DISPORDER": "20032",
        "CA7uXs6D": "99",
        "P_DISP_DICTIONARY": "0",
        "P_ICON_ID": "655",
        "60IsqxDt": "1",
        "o7e4HXMP": "0,0,0,1,0,0,0,0",
        "P_DOUBLE_SPHERE_TRIGGER": "0,0,0,0",
        "P_DICTIONARY_NO": "1",
        "P_DICTIONARY_BG": "91",
        "T04pJPmh": "",
        "P_NEED_SWITCH_INFO": "0",
        "P_HIDE_SWITCH_INFO": "0",
        "P_OPEN_SWITCH_INFO": "0"
    },
    {
        "P_ELEMENT_ITEM_ID": "20033",
        "P_NAME": "\u5ba3\u5091\u5ca9",
        "8Cx57oAk": "\u5ba3\u5091\u5ca9",
        "P_RARE": "4",
        "P_DISPORDER": "20033",
        "CA7uXs6D": "99",
        "P_DISP_DICTIONARY": "0",
        "P_ICON_ID": "555",
        "60IsqxDt": "1",
        "o7e4HXMP": "0,0,0,1,0,0,0,0",
        "P_DOUBLE_SPHERE_TRIGGER": "0,0,0,0",
        "P_DICTIONARY_NO": "1",
        "P_DICTIONARY_BG": "92",
        "T04pJPmh": "",
        "P_NEED_SWITCH_INFO": "0",
        "P_HIDE_SWITCH_INFO": "0",
        "P_OPEN_SWITCH_INFO": "0"
    },
    {
        "P_ELEMENT_ITEM_ID": "20034",
        "P_NAME": "\u8ee2\u9234\u77f3",
        "8Cx57oAk": "\u8ee2\u9234\u77f3",
        "P_RARE": "4",
        "P_DISPORDER": "20034",
        "CA7uXs6D": "99",
        "P_DISP_DICTIONARY": "0",
        "P_ICON_ID": "405",
        "60IsqxDt": "1",
        "o7e4HXMP": "0,0,0,1,0,0,0,0",
        "P_DOUBLE_SPHERE_TRIGGER": "0,0,0,0",
        "P_DICTIONARY_NO": "1",
        "P_DICTIONARY_BG": "93",
        "T04pJPmh": "",
        "P_NEED_SWITCH_INFO": "0",
        "P_HIDE_SWITCH_INFO": "0",
        "P_OPEN_SWITCH_INFO": "0"
    },
    {
        "P_ELEMENT_ITEM_ID": "20035",
        "P_NAME": "\u6d44\u697d\u306e\u91d1\u7fc5",
        "8Cx57oAk": "\u6d44\u697d\u91d1\u7fc5",
        "P_RARE": "4",
        "P_DISPORDER": "20035",
        "CA7uXs6D": "99",
        "P_DISP_DICTIONARY": "0",
        "P_ICON_ID": "152",
        "60IsqxDt": "1",
        "o7e4HXMP": "0,0,0,1,0,0,0,0",
        "P_DOUBLE_SPHERE_TRIGGER": "0,0,0,0",
        "P_DICTIONARY_NO": "1",
        "P_DICTIONARY_BG": "94",
        "T04pJPmh": "",
        "P_NEED_SWITCH_INFO": "0",
        "P_HIDE_SWITCH_INFO": "0",
        "P_OPEN_SWITCH_INFO": "0"
    },
    {
        "P_ELEMENT_ITEM_ID": "30000",
        "P_NAME": "\u5bb5\u73bb\u7483",
        "8Cx57oAk": "\u5bb5\u73bb\u7483",
        "P_RARE": "5",
        "P_DISPORDER": "30000",
        "CA7uXs6D": "99",
        "P_DISP_DICTIONARY": "1",
        "P_ICON_ID": "805",
        "60IsqxDt": "1",
        "o7e4HXMP": "0,0,0,1,0,0,0,0",
        "P_DOUBLE_SPHERE_TRIGGER": "0,0,0,0",
        "P_DICTIONARY_NO": "1",
        "P_DICTIONARY_BG": "63",
        "T04pJPmh": "",
        "P_NEED_SWITCH_INFO": "0",
        "P_HIDE_SWITCH_INFO": "0",
        "P_OPEN_SWITCH_INFO": "0"
    },
    {
        "P_ELEMENT_ITEM_ID": "30011",
        "P_NAME": "\u30d0\u30fc\u30b9\u30c8\u30af\u30c3\u30ad\u30fc",
        "8Cx57oAk": "\u30af\u30c3\u30ad\u30fc",
        "P_RARE": "5",
        "P_DISPORDER": "30011",
        "CA7uXs6D": "99",
        "P_DISP_DICTIONARY": "2",
        "P_ICON_ID": "16",
        "60IsqxDt": "1",
        "o7e4HXMP": "0,0,0,0,0,0,1,0",
        "P_DOUBLE_SPHERE_TRIGGER": "0,0,0,0",
        "P_DICTIONARY_NO": "1",
        "P_DICTIONARY_BG": "1",
        "T04pJPmh": "",
        "P_NEED_SWITCH_INFO": "0",
        "P_HIDE_SWITCH_INFO": "0",
        "P_OPEN_SWITCH_INFO": "0"
    },
    {
        "P_ELEMENT_ITEM_ID": "30012",
        "P_NAME": "\uff22\uff30\u30ad\u30e3\u30f3\u30c7\u30a3",
        "8Cx57oAk": "\uff22\uff30\u98f4",
        "P_RARE": "5",
        "P_DISPORDER": "30012",
        "CA7uXs6D": "99",
        "P_DISP_DICTIONARY": "2",
        "P_ICON_ID": "17",
        "60IsqxDt": "1",
        "o7e4HXMP": "0,0,0,0,0,0,1,0",
        "P_DOUBLE_SPHERE_TRIGGER": "0,0,0,0",
        "P_DICTIONARY_NO": "1",
        "P_DICTIONARY_BG": "72",
        "T04pJPmh": "",
        "P_NEED_SWITCH_INFO": "0",
        "P_HIDE_SWITCH_INFO": "0",
        "P_OPEN_SWITCH_INFO": "0"
    },
    {
        "P_ELEMENT_ITEM_ID": "40000",
        "P_NAME": "\u8056\u8679\u306e\u970a\u9b42",
        "8Cx57oAk": "\u8056\u8679\u970a\u9b42",
        "P_RARE": "5",
        "P_DISPORDER": "40000",
        "CA7uXs6D": "99",
        "P_DISP_DICTIONARY": "1",
        "P_ICON_ID": "900",
        "60IsqxDt": "1",
        "o7e4HXMP": "0,0,0,1,0,0,0,0",
        "P_DOUBLE_SPHERE_TRIGGER": "0,0,0,0",
        "P_DICTIONARY_NO": "1",
        "P_DICTIONARY_BG": "83",
        "T04pJPmh": "",
        "P_NEED_SWITCH_INFO": "0",
        "P_HIDE_SWITCH_INFO": "0",
        "P_OPEN_SWITCH_INFO": "0"
    }
]